codon_compiler_demo/__init__.py
codon_compiler_demo/cli.py
codon_compiler_demo/find_shared_lib.py
codon_compiler_demo/paths.py
codon_compiler_demo/setup_tools.py
codon_compiler_demo/binaries/linux-x86_64/bin/codon
codon_compiler_demo/binaries/linux-x86_64/include/peglib.h
codon_compiler_demo/binaries/linux-x86_64/include/codon/cir/attribute.h
codon_compiler_demo/binaries/linux-x86_64/include/codon/cir/base.h
codon_compiler_demo/binaries/linux-x86_64/include/codon/cir/cir.h
codon_compiler_demo/binaries/linux-x86_64/include/codon/cir/const.h
codon_compiler_demo/binaries/linux-x86_64/include/codon/cir/flow.h
codon_compiler_demo/binaries/linux-x86_64/include/codon/cir/func.h
codon_compiler_demo/binaries/linux-x86_64/include/codon/cir/instr.h
codon_compiler_demo/binaries/linux-x86_64/include/codon/cir/module.h
codon_compiler_demo/binaries/linux-x86_64/include/codon/cir/pyextension.h
codon_compiler_demo/binaries/linux-x86_64/include/codon/cir/value.h
codon_compiler_demo/binaries/linux-x86_64/include/codon/cir/var.h
codon_compiler_demo/binaries/linux-x86_64/include/codon/cir/analyze/analysis.h
codon_compiler_demo/binaries/linux-x86_64/include/codon/cir/analyze/dataflow/capture.h
codon_compiler_demo/binaries/linux-x86_64/include/codon/cir/analyze/dataflow/cfg.h
codon_compiler_demo/binaries/linux-x86_64/include/codon/cir/analyze/dataflow/dominator.h
codon_compiler_demo/binaries/linux-x86_64/include/codon/cir/analyze/dataflow/reaching.h
codon_compiler_demo/binaries/linux-x86_64/include/codon/cir/analyze/module/global_vars.h
codon_compiler_demo/binaries/linux-x86_64/include/codon/cir/analyze/module/side_effect.h
codon_compiler_demo/binaries/linux-x86_64/include/codon/cir/dsl/codegen.h
codon_compiler_demo/binaries/linux-x86_64/include/codon/cir/dsl/nodes.h
codon_compiler_demo/binaries/linux-x86_64/include/codon/cir/llvm/gpu.h
codon_compiler_demo/binaries/linux-x86_64/include/codon/cir/llvm/llvisitor.h
codon_compiler_demo/binaries/linux-x86_64/include/codon/cir/llvm/llvm.h
codon_compiler_demo/binaries/linux-x86_64/python/codon_jit.egg-info/PKG-INFO
codon_compiler_demo/binaries/linux-x86_64/python/codon_jit.egg-info/SOURCES.txt
codon_compiler_demo/binaries/linux-x86_64/python/codon_jit.egg-info/dependency_links.txt
codon_compiler_demo/binaries/linux-x86_64/python/codon_jit.egg-info/requires.txt
codon_compiler_demo/binaries/linux-x86_64/python/codon_jit.egg-info/top_level.txt
codon_compiler_demo-0.18.0.dist-info/METADATA
codon_compiler_demo-0.18.0.dist-info/WHEEL
codon_compiler_demo-0.18.0.dist-info/entry_points.txt
codon_compiler_demo-0.18.0.dist-info/top_level.txt
codon_compiler_demo-0.18.0.dist-info/RECORD
