Metadata-Version: 2.2
Name: codon-compiler-demo
Version: 0.18.0
Summary: A compiled language similar to Python. Compatible with Python syntax.
Classifier: Programming Language :: Python
Classifier: Operating System :: POSIX :: Linux
Requires-Python: >=3.6
Dynamic: classifier
Dynamic: description
Dynamic: description-content-type
Dynamic: requires-python
Dynamic: summary
